[
  {
    "period": "2017.11.8",
    "index": "50.6939"
  },
  {
    "period": "2017.11.9",
    "index": "49.1544"
  },
  {
    "period": "2017.11.10",
    "index": "42.0317"
  },
  {
    "period": "2017.11.11",
    "index": "35.6318"
  },
  {
    "period": "2017.11.12",
    "index": "40.2203"
  },
  {
    "period": "2017.11.13",
    "index": "50.6863"
  },
  {
    "period": "2017.11.14",
    "index": "47.7552"
  },
  {
    "period": "2017.11.15",
    "index": "44.43"
  },
  {
    "period": "2017.11.16",
    "index": "44.9167"
  },
  {
    "period": "2017.11.17",
    "index": "37.3281"
  },
  {
    "period": "2017.11.18",
    "index": "31.2199"
  },
  {
    "period": "2017.11.19",
    "index": "40.3761"
  },
  {
    "period": "2017.11.20",
    "index": "46.4567"
  },
  {
    "period": "2017.11.21",
    "index": "44.3709"
  },
  {
    "period": "2017.11.22",
    "index": "42.9423"
  },
  {
    "period": "2017.11.23",
    "index": "39.6749"
  },
  {
    "period": "2017.11.24",
    "index": "33.1794"
  },
  {
    "period": "2017.11.25",
    "index": "30.3133"
  },
  {
    "period": "2017.11.26",
    "index": "34.8774"
  },
  {
    "period": "2017.11.27",
    "index": "42.638"
  },
  {
    "period": "2017.11.28",
    "index": "42.8638"
  },
  {
    "period": "2017.11.29",
    "index": "44.1126"
  },
  {
    "period": "2017.11.30",
    "index": "40.7716"
  },
  {
    "period": "2017.12.1",
    "index": "35.0679"
  },
  {
    "period": "2017.12.2",
    "index": "29.6162"
  },
  {
    "period": "2017.12.3",
    "index": "36.8856"
  },
  {
    "period": "2017.12.4",
    "index": "43.2471"
  },
  {
    "period": "2017.12.5",
    "index": "44.7645"
  },
  {
    "period": "2017.12.6",
    "index": "41.2827"
  },
  {
    "period": "2017.12.7",
    "index": "39.0799"
  },
  {
    "period": "2017.12.8",
    "index": "33.518"
  },
  {
    "period": "2017.12.9",
    "index": "27.7755"
  },
  {
    "period": "2017.12.10",
    "index": "34.4164"
  },
  {
    "period": "2017.12.11",
    "index": "40.5282"
  },
  {
    "period": "2017.12.12",
    "index": "39.9038"
  },
  {
    "period": "2017.12.13",
    "index": "38.9246"
  },
  {
    "period": "2017.12.14",
    "index": "35.5271"
  },
  {
    "period": "2017.12.15",
    "index": "29.8799"
  },
  {
    "period": "2017.12.16",
    "index": "25.7659"
  },
  {
    "period": "2017.12.17",
    "index": "31.6926"
  },
  {
    "period": "2017.12.18",
    "index": "36.5263"
  },
  {
    "period": "2017.12.19",
    "index": "35.5492"
  },
  {
    "period": "2017.12.20",
    "index": "33.3694"
  },
  {
    "period": "2017.12.21",
    "index": "30.1535"
  },
  {
    "period": "2017.12.22",
    "index": "24.4697"
  },
  {
    "period": "2017.12.23",
    "index": "22.1852"
  },
  {
    "period": "2017.12.24",
    "index": "23.5379"
  },
  {
    "period": "2017.12.25",
    "index": "28.6645"
  },
  {
    "period": "2017.12.26",
    "index": "36.0924"
  },
  {
    "period": "2017.12.27",
    "index": "34.7266"
  },
  {
    "period": "2017.12.28",
    "index": "32.3902"
  },
  {
    "period": "2017.12.29",
    "index": "26.9209"
  },
  {
    "period": "2017.12.30",
    "index": "24.2932"
  },
  {
    "period": "2017.12.31",
    "index": "24.1072"
  },
  {
    "period": "2018.1.1",
    "index": "31.0402"
  },
  {
    "period": "2018.1.2",
    "index": "39.6271"
  },
  {
    "period": "2018.1.3",
    "index": "39.8894"
  },
  {
    "period": "2018.1.4",
    "index": "37.4383"
  },
  {
    "period": "2018.1.5",
    "index": "33.8584"
  },
  {
    "period": "2018.1.6",
    "index": "29.7724"
  },
  {
    "period": "2018.1.7",
    "index": "37.3651"
  },
  {
    "period": "2018.1.8",
    "index": "41.7942"
  },
  {
    "period": "2018.1.9",
    "index": "40.5571"
  },
  {
    "period": "2018.1.10",
    "index": "38.246"
  },
  {
    "period": "2018.1.11",
    "index": "37.4197"
  },
  {
    "period": "2018.1.12",
    "index": "33.229"
  },
  {
    "period": "2018.1.13",
    "index": "29.8117"
  },
  {
    "period": "2018.1.14",
    "index": "35.2323"
  },
  {
    "period": "2018.1.15",
    "index": "41.5919"
  },
  {
    "period": "2018.1.16",
    "index": "41.9134"
  },
  {
    "period": "2018.1.17",
    "index": "39.9237"
  },
  {
    "period": "2018.1.18",
    "index": "37.3498"
  },
  {
    "period": "2018.1.19",
    "index": "32.3161"
  },
  {
    "period": "2018.1.20",
    "index": "28.7724"
  },
  {
    "period": "2018.1.21",
    "index": "34.9546"
  },
  {
    "period": "2018.1.22",
    "index": "41.9622"
  },
  {
    "period": "2018.1.23",
    "index": "41.5536"
  },
  {
    "period": "2018.1.24",
    "index": "40.8777"
  },
  {
    "period": "2018.1.25",
    "index": "38.674"
  },
  {
    "period": "2018.1.26",
    "index": "33.1067"
  },
  {
    "period": "2018.1.27",
    "index": "31.2168"
  },
  {
    "period": "2018.1.28",
    "index": "42.0407"
  },
  {
    "period": "2018.1.29",
    "index": "43.5505"
  },
  {
    "period": "2018.1.30",
    "index": "41.3734"
  },
  {
    "period": "2018.1.31",
    "index": "40.1851"
  },
  {
    "period": "2018.2.1",
    "index": "39.0979"
  },
  {
    "period": "2018.2.2",
    "index": "36.2147"
  },
  {
    "period": "2018.2.3",
    "index": "33.3884"
  },
  {
    "period": "2018.2.4",
    "index": "40.5395"
  },
  {
    "period": "2018.2.5",
    "index": "46.915"
  },
  {
    "period": "2018.2.6",
    "index": "44.9248"
  },
  {
    "period": "2018.2.7",
    "index": "42.2683"
  },
  {
    "period": "2018.2.8",
    "index": "39.0103"
  },
  {
    "period": "2018.2.9",
    "index": "32.3942"
  },
  {
    "period": "2018.2.10",
    "index": "28.7142"
  },
  {
    "period": "2018.2.11",
    "index": "33.7333"
  },
  {
    "period": "2018.2.12",
    "index": "34.0042"
  },
  {
    "period": "2018.2.13",
    "index": "29.4568"
  },
  {
    "period": "2018.2.14",
    "index": "23.9397"
  },
  {
    "period": "2018.2.15",
    "index": "20.2722"
  },
  {
    "period": "2018.2.16",
    "index": "20.3097"
  },
  {
    "period": "2018.2.17",
    "index": "28.2275"
  },
  {
    "period": "2018.2.18",
    "index": "38.5724"
  },
  {
    "period": "2018.2.19",
    "index": "45.3375"
  },
  {
    "period": "2018.2.20",
    "index": "44.1862"
  },
  {
    "period": "2018.2.21",
    "index": "43.4846"
  },
  {
    "period": "2018.2.22",
    "index": "42.829"
  },
  {
    "period": "2018.2.23",
    "index": "37.6685"
  },
  {
    "period": "2018.2.24",
    "index": "36.1479"
  },
  {
    "period": "2018.2.25",
    "index": "42.41"
  },
  {
    "period": "2018.2.26",
    "index": "49.9314"
  },
  {
    "period": "2018.2.27",
    "index": "49.3508"
  },
  {
    "period": "2018.2.28",
    "index": "45.6833"
  },
  {
    "period": "2018.3.1",
    "index": "47.2057"
  },
  {
    "period": "2018.3.2",
    "index": "44.3681"
  },
  {
    "period": "2018.3.3",
    "index": "40.1093"
  },
  {
    "period": "2018.3.4",
    "index": "48.1363"
  },
  {
    "period": "2018.3.5",
    "index": "52.8398"
  },
  {
    "period": "2018.3.6",
    "index": "49.8578"
  },
  {
    "period": "2018.3.7",
    "index": "47.6857"
  },
  {
    "period": "2018.3.8",
    "index": "46.8951"
  },
  {
    "period": "2018.3.9",
    "index": "36.6789"
  },
  {
    "period": "2018.3.10",
    "index": "31.6001"
  },
  {
    "period": "2018.3.11",
    "index": "37.8803"
  },
  {
    "period": "2018.3.12",
    "index": "46.2495"
  },
  {
    "period": "2018.3.13",
    "index": "42.6489"
  },
  {
    "period": "2018.3.14",
    "index": "40.2993"
  },
  {
    "period": "2018.3.15",
    "index": "41.6791"
  },
  {
    "period": "2018.3.16",
    "index": "34.4589"
  },
  {
    "period": "2018.3.17",
    "index": "30.8628"
  },
  {
    "period": "2018.3.18",
    "index": "38.6428"
  },
  {
    "period": "2018.3.19",
    "index": "44.2205"
  },
  {
    "period": "2018.3.20",
    "index": "43.2078"
  },
  {
    "period": "2018.3.21",
    "index": "43.2949"
  },
  {
    "period": "2018.3.22",
    "index": "40.8154"
  },
  {
    "period": "2018.3.23",
    "index": "35.2047"
  },
  {
    "period": "2018.3.24",
    "index": "32.694"
  },
  {
    "period": "2018.3.25",
    "index": "38.3539"
  },
  {
    "period": "2018.3.26",
    "index": "44.3424"
  },
  {
    "period": "2018.3.27",
    "index": "43.7975"
  },
  {
    "period": "2018.3.28",
    "index": "42.2854"
  },
  {
    "period": "2018.3.29",
    "index": "40.5115"
  },
  {
    "period": "2018.3.30",
    "index": "35.9343"
  },
  {
    "period": "2018.3.31",
    "index": "32.0123"
  },
  {
    "period": "2018.4.1",
    "index": "41.1183"
  },
  {
    "period": "2018.4.2",
    "index": "46.045"
  },
  {
    "period": "2018.4.3",
    "index": "46.8251"
  },
  {
    "period": "2018.4.4",
    "index": "48.2288"
  },
  {
    "period": "2018.4.5",
    "index": "51.5143"
  },
  {
    "period": "2018.4.6",
    "index": "40.7978"
  },
  {
    "period": "2018.4.7",
    "index": "34.8553"
  },
  {
    "period": "2018.4.8",
    "index": "42.5906"
  },
  {
    "period": "2018.4.9",
    "index": "52.3067"
  },
  {
    "period": "2018.4.10",
    "index": "53.3496"
  },
  {
    "period": "2018.4.11",
    "index": "52.0809"
  },
  {
    "period": "2018.4.12",
    "index": "48.8175"
  },
  {
    "period": "2018.4.13",
    "index": "44.681"
  },
  {
    "period": "2018.4.14",
    "index": "41.55"
  },
  {
    "period": "2018.4.15",
    "index": "47.4947"
  },
  {
    "period": "2018.4.16",
    "index": "55.1984"
  },
  {
    "period": "2018.4.17",
    "index": "55.7574"
  },
  {
    "period": "2018.4.18",
    "index": "53.2119"
  },
  {
    "period": "2018.4.19",
    "index": "49.9788"
  },
  {
    "period": "2018.4.20",
    "index": "45.337"
  },
  {
    "period": "2018.4.21",
    "index": "37.3922"
  },
  {
    "period": "2018.4.22",
    "index": "48.7209"
  },
  {
    "period": "2018.4.23",
    "index": "58.6505"
  },
  {
    "period": "2018.4.24",
    "index": "52.9992"
  },
  {
    "period": "2018.4.25",
    "index": "48.2681"
  },
  {
    "period": "2018.4.26",
    "index": "47.2021"
  },
  {
    "period": "2018.4.27",
    "index": "39.8591"
  },
  {
    "period": "2018.4.28",
    "index": "34.5514"
  },
  {
    "period": "2018.4.29",
    "index": "41.0958"
  },
  {
    "period": "2018.4.30",
    "index": "45.8924"
  },
  {
    "period": "2018.5.1",
    "index": "47.3407"
  },
  {
    "period": "2018.5.2",
    "index": "49.1336"
  },
  {
    "period": "2018.5.3",
    "index": "43.2114"
  },
  {
    "period": "2018.5.4",
    "index": "35.9199"
  },
  {
    "period": "2018.5.5",
    "index": "28.5313"
  },
  {
    "period": "2018.5.6",
    "index": "36.2978"
  },
  {
    "period": "2018.5.7",
    "index": "41.6484"
  },
  {
    "period": "2018.5.8",
    "index": "46.1678"
  },
  {
    "period": "2018.5.9",
    "index": "48.8004"
  },
  {
    "period": "2018.5.10",
    "index": "46.2721"
  },
  {
    "period": "2018.5.11",
    "index": "41.503"
  },
  {
    "period": "2018.5.12",
    "index": "39.0067"
  },
  {
    "period": "2018.5.13",
    "index": "40.7441"
  },
  {
    "period": "2018.5.14",
    "index": "49.5684"
  },
  {
    "period": "2018.5.15",
    "index": "48.4017"
  },
  {
    "period": "2018.5.16",
    "index": "48.4595"
  },
  {
    "period": "2018.5.17",
    "index": "45.0363"
  },
  {
    "period": "2018.5.18",
    "index": "37.3773"
  },
  {
    "period": "2018.5.19",
    "index": "30.3589"
  },
  {
    "period": "2018.5.20",
    "index": "37.4495"
  },
  {
    "period": "2018.5.21",
    "index": "41.4971"
  },
  {
    "period": "2018.5.22",
    "index": "46.0418"
  },
  {
    "period": "2018.5.23",
    "index": "49.6542"
  },
  {
    "period": "2018.5.24",
    "index": "46.5718"
  },
  {
    "period": "2018.5.25",
    "index": "41.3066"
  },
  {
    "period": "2018.5.26",
    "index": "35.2955"
  },
  {
    "period": "2018.5.27",
    "index": "43.7324"
  },
  {
    "period": "2018.5.28",
    "index": "52.7807"
  },
  {
    "period": "2018.5.29",
    "index": "53.2642"
  },
  {
    "period": "2018.5.30",
    "index": "49.7056"
  },
  {
    "period": "2018.5.31",
    "index": "46.752"
  },
  {
    "period": "2018.6.1",
    "index": "44.6169"
  },
  {
    "period": "2018.6.2",
    "index": "39.1006"
  },
  {
    "period": "2018.6.3",
    "index": "48.0712"
  },
  {
    "period": "2018.6.4",
    "index": "57.4446"
  },
  {
    "period": "2018.6.5",
    "index": "50.0677"
  },
  {
    "period": "2018.6.6",
    "index": "51.4764"
  },
  {
    "period": "2018.6.7",
    "index": "53.2173"
  },
  {
    "period": "2018.6.8",
    "index": "44.5961"
  },
  {
    "period": "2018.6.9",
    "index": "38.9999"
  },
  {
    "period": "2018.6.10",
    "index": "48.6812"
  },
  {
    "period": "2018.6.11",
    "index": "53.8462"
  },
  {
    "period": "2018.6.12",
    "index": "47.0811"
  },
  {
    "period": "2018.6.13",
    "index": "46.1001"
  },
  {
    "period": "2018.6.14",
    "index": "48.5132"
  },
  {
    "period": "2018.6.15",
    "index": "42.6037"
  },
  {
    "period": "2018.6.16",
    "index": "37.394"
  },
  {
    "period": "2018.6.17",
    "index": "46.5023"
  },
  {
    "period": "2018.6.18",
    "index": "53.5252"
  },
  {
    "period": "2018.6.19",
    "index": "51.8506"
  },
  {
    "period": "2018.6.20",
    "index": "50.381"
  },
  {
    "period": "2018.6.21",
    "index": "49.8551"
  },
  {
    "period": "2018.6.22",
    "index": "44.5794"
  },
  {
    "period": "2018.6.23",
    "index": "37.6256"
  },
  {
    "period": "2018.6.24",
    "index": "42.7658"
  },
  {
    "period": "2018.6.25",
    "index": "53.7577"
  },
  {
    "period": "2018.6.26",
    "index": "51.5454"
  },
  {
    "period": "2018.6.27",
    "index": "46.9209"
  },
  {
    "period": "2018.6.28",
    "index": "41.861"
  },
  {
    "period": "2018.6.29",
    "index": "39.679"
  },
  {
    "period": "2018.6.30",
    "index": "36.6834"
  },
  {
    "period": "2018.7.1",
    "index": "47.2712"
  },
  {
    "period": "2018.7.2",
    "index": "52.6376"
  },
  {
    "period": "2018.7.3",
    "index": "49.5909"
  },
  {
    "period": "2018.7.4",
    "index": "49.9341"
  },
  {
    "period": "2018.7.5",
    "index": "48.7304"
  },
  {
    "period": "2018.7.6",
    "index": "42.2024"
  },
  {
    "period": "2018.7.7",
    "index": "37.2608"
  },
  {
    "period": "2018.7.8",
    "index": "45.4309"
  },
  {
    "period": "2018.7.9",
    "index": "52.9572"
  },
  {
    "period": "2018.7.10",
    "index": "49.8695"
  },
  {
    "period": "2018.7.11",
    "index": "49.6235"
  },
  {
    "period": "2018.7.12",
    "index": "48.5011"
  },
  {
    "period": "2018.7.13",
    "index": "42.6317"
  },
  {
    "period": "2018.7.14",
    "index": "38.4338"
  },
  {
    "period": "2018.7.15",
    "index": "49.5016"
  },
  {
    "period": "2018.7.16",
    "index": "60.8849"
  },
  {
    "period": "2018.7.17",
    "index": "56.9651"
  },
  {
    "period": "2018.7.18",
    "index": "58.1674"
  },
  {
    "period": "2018.7.19",
    "index": "55.6892"
  },
  {
    "period": "2018.7.20",
    "index": "47.9737"
  },
  {
    "period": "2018.7.21",
    "index": "42.5992"
  },
  {
    "period": "2018.7.22",
    "index": "53.4566"
  },
  {
    "period": "2018.7.23",
    "index": "63.9875"
  },
  {
    "period": "2018.7.24",
    "index": "62.82"
  },
  {
    "period": "2018.7.25",
    "index": "56.7822"
  },
  {
    "period": "2018.7.26",
    "index": "54.8657"
  },
  {
    "period": "2018.7.27",
    "index": "45.9375"
  },
  {
    "period": "2018.7.28",
    "index": "39.4411"
  },
  {
    "period": "2018.7.29",
    "index": "46.3154"
  },
  {
    "period": "2018.7.30",
    "index": "54.0995"
  },
  {
    "period": "2018.7.31",
    "index": "52.6615"
  },
  {
    "period": "2018.8.1",
    "index": "52.5604"
  },
  {
    "period": "2018.8.2",
    "index": "52.0949"
  },
  {
    "period": "2018.8.3",
    "index": "45.6829"
  },
  {
    "period": "2018.8.4",
    "index": "42.8575"
  },
  {
    "period": "2018.8.5",
    "index": "48.7196"
  },
  {
    "period": "2018.8.6",
    "index": "56.1479"
  },
  {
    "period": "2018.8.7",
    "index": "55.1727"
  },
  {
    "period": "2018.8.8",
    "index": "55.2607"
  },
  {
    "period": "2018.8.9",
    "index": "53.7054"
  },
  {
    "period": "2018.8.10",
    "index": "49.2257"
  },
  {
    "period": "2018.8.11",
    "index": "44.9488"
  },
  {
    "period": "2018.8.12",
    "index": "50.0348"
  },
  {
    "period": "2018.8.13",
    "index": "56.6003"
  },
  {
    "period": "2018.8.14",
    "index": "50.7418"
  },
  {
    "period": "2018.8.15",
    "index": "53.0818"
  },
  {
    "period": "2018.8.16",
    "index": "55.3695"
  },
  {
    "period": "2018.8.17",
    "index": "44.891"
  },
  {
    "period": "2018.8.18",
    "index": "37.8568"
  },
  {
    "period": "2018.8.19",
    "index": "43.0186"
  },
  {
    "period": "2018.8.20",
    "index": "50.6885"
  },
  {
    "period": "2018.8.21",
    "index": "49.9038"
  },
  {
    "period": "2018.8.22",
    "index": "49.4605"
  },
  {
    "period": "2018.8.23",
    "index": "45.3393"
  },
  {
    "period": "2018.8.24",
    "index": "41.1766"
  },
  {
    "period": "2018.8.25",
    "index": "36.5868"
  },
  {
    "period": "2018.8.26",
    "index": "43.0444"
  },
  {
    "period": "2018.8.27",
    "index": "47.9385"
  },
  {
    "period": "2018.8.28",
    "index": "48.3033"
  },
  {
    "period": "2018.8.29",
    "index": "45.1682"
  },
  {
    "period": "2018.8.30",
    "index": "44.4304"
  },
  {
    "period": "2018.8.31",
    "index": "39.1377"
  },
  {
    "period": "2018.9.1",
    "index": "33.895"
  },
  {
    "period": "2018.9.2",
    "index": "41.5174"
  },
  {
    "period": "2018.9.3",
    "index": "50.8073"
  },
  {
    "period": "2018.9.4",
    "index": "51.3043"
  },
  {
    "period": "2018.9.5",
    "index": "49.4505"
  },
  {
    "period": "2018.9.6",
    "index": "45.821"
  },
  {
    "period": "2018.9.7",
    "index": "41.1563"
  },
  {
    "period": "2018.9.8",
    "index": "33.5491"
  },
  {
    "period": "2018.9.9",
    "index": "41.2168"
  },
  {
    "period": "2018.9.10",
    "index": "49.8022"
  },
  {
    "period": "2018.9.11",
    "index": "48.1539"
  },
  {
    "period": "2018.9.12",
    "index": "46.9227"
  },
  {
    "period": "2018.9.13",
    "index": "44.2119"
  },
  {
    "period": "2018.9.14",
    "index": "38.7995"
  },
  {
    "period": "2018.9.15",
    "index": "33.7835"
  },
  {
    "period": "2018.9.16",
    "index": "40.7206"
  },
  {
    "period": "2018.9.17",
    "index": "45.1984"
  },
  {
    "period": "2018.9.18",
    "index": "41.0714"
  },
  {
    "period": "2018.9.19",
    "index": "36.0851"
  },
  {
    "period": "2018.9.20",
    "index": "32.4945"
  },
  {
    "period": "2018.9.21",
    "index": "25.9935"
  },
  {
    "period": "2018.9.22",
    "index": "22.0922"
  },
  {
    "period": "2018.9.23",
    "index": "21.4389"
  },
  {
    "period": "2018.9.24",
    "index": "21.6041"
  },
  {
    "period": "2018.9.25",
    "index": "28.9169"
  },
  {
    "period": "2018.9.26",
    "index": "42.2457"
  },
  {
    "period": "2018.9.27",
    "index": "46.808"
  },
  {
    "period": "2018.9.28",
    "index": "42.0795"
  },
  {
    "period": "2018.9.29",
    "index": "37.7466"
  },
  {
    "period": "2018.9.30",
    "index": "44.8205"
  },
  {
    "period": "2018.10.1",
    "index": "50.6537"
  },
  {
    "period": "2018.10.2",
    "index": "43.8923"
  },
  {
    "period": "2018.10.3",
    "index": "42.2258"
  },
  {
    "period": "2018.10.4",
    "index": "47.0509"
  },
  {
    "period": "2018.10.5",
    "index": "45.8364"
  },
  {
    "period": "2018.10.6",
    "index": "39.7914"
  },
  {
    "period": "2018.10.7",
    "index": "40.7766"
  },
  {
    "period": "2018.10.8",
    "index": "44.0354"
  },
  {
    "period": "2018.10.9",
    "index": "45.3808"
  },
  {
    "period": "2018.10.10",
    "index": "51.1806"
  },
  {
    "period": "2018.10.11",
    "index": "49.418"
  },
  {
    "period": "2018.10.12",
    "index": "41.41"
  },
  {
    "period": "2018.10.13",
    "index": "34.0318"
  },
  {
    "period": "2018.10.14",
    "index": "43.2683"
  },
  {
    "period": "2018.10.15",
    "index": "52.9812"
  },
  {
    "period": "2018.10.16",
    "index": "51.2046"
  },
  {
    "period": "2018.10.17",
    "index": "48.7972"
  },
  {
    "period": "2018.10.18",
    "index": "46.2991"
  },
  {
    "period": "2018.10.19",
    "index": "39.9386"
  },
  {
    "period": "2018.10.20",
    "index": "33.3997"
  },
  {
    "period": "2018.10.21",
    "index": "41.3657"
  },
  {
    "period": "2018.10.22",
    "index": "49.2776"
  },
  {
    "period": "2018.10.23",
    "index": "48.3697"
  },
  {
    "period": "2018.10.24",
    "index": "45.3266"
  },
  {
    "period": "2018.10.25",
    "index": "42.8823"
  },
  {
    "period": "2018.10.26",
    "index": "39.1467"
  },
  {
    "period": "2018.10.27",
    "index": "35.7844"
  },
  {
    "period": "2018.10.28",
    "index": "46.1091"
  },
  {
    "period": "2018.10.29",
    "index": "52.0208"
  },
  {
    "period": "2018.10.30",
    "index": "47.2572"
  },
  {
    "period": "2018.10.31",
    "index": "43.7713"
  },
  {
    "period": "2018.11.1",
    "index": "47.6003"
  },
  {
    "period": "2018.11.2",
    "index": "38.3751"
  },
  {
    "period": "2018.11.3",
    "index": "37.7263"
  },
  {
    "period": "2018.11.4",
    "index": "43.8905"
  },
  {
    "period": "2018.11.5",
    "index": "49.5887"
  },
  {
    "period": "2018.11.6",
    "index": "50.8452"
  },
  {
    "period": "2018.11.7",
    "index": "52.1802"
  },
  {
    "period": "2018.11.8",
    "index": "51.1928"
  },
  {
    "period": "2018.11.9",
    "index": "41.6511"
  },
  {
    "period": "2018.11.10",
    "index": "34.7952"
  },
  {
    "period": "2018.11.11",
    "index": "45.5917"
  },
  {
    "period": "2018.11.12",
    "index": "50.842"
  },
  {
    "period": "2018.11.13",
    "index": "47.7764"
  },
  {
    "period": "2018.11.14",
    "index": "44.1907"
  },
  {
    "period": "2018.11.15",
    "index": "40.4465"
  },
  {
    "period": "2018.11.16",
    "index": "35.9005"
  },
  {
    "period": "2018.11.17",
    "index": "31.6886"
  },
  {
    "period": "2018.11.18",
    "index": "38.7142"
  },
  {
    "period": "2018.11.19",
    "index": "46.6188"
  },
  {
    "period": "2018.11.20",
    "index": "44.1699"
  },
  {
    "period": "2018.11.21",
    "index": "41.922"
  },
  {
    "period": "2018.11.22",
    "index": "39.8022"
  },
  {
    "period": "2018.11.23",
    "index": "34.0146"
  },
  {
    "period": "2018.11.24",
    "index": "31.117"
  },
  {
    "period": "2018.11.25",
    "index": "37.4197"
  },
  {
    "period": "2018.11.26",
    "index": "44.3591"
  },
  {
    "period": "2018.11.27",
    "index": "43.7392"
  },
  {
    "period": "2018.11.28",
    "index": "42.9342"
  },
  {
    "period": "2018.11.29",
    "index": "39.9237"
  },
  {
    "period": "2018.11.30",
    "index": "33.5279"
  },
  {
    "period": "2018.12.1",
    "index": "31.1811"
  },
  {
    "period": "2018.12.2",
    "index": "39.6429"
  },
  {
    "period": "2018.12.3",
    "index": "45.3113"
  },
  {
    "period": "2018.12.4",
    "index": "43.4444"
  },
  {
    "period": "2018.12.5",
    "index": "44.2367"
  },
  {
    "period": "2018.12.6",
    "index": "39.9549"
  },
  {
    "period": "2018.12.7",
    "index": "33.7789"
  },
  {
    "period": "2018.12.8",
    "index": "29.9472"
  },
  {
    "period": "2018.12.9",
    "index": "36.7339"
  },
  {
    "period": "2018.12.10",
    "index": "42.1563"
  },
  {
    "period": "2018.12.11",
    "index": "42.7762"
  },
  {
    "period": "2018.12.12",
    "index": "39.9567"
  },
  {
    "period": "2018.12.13",
    "index": "37.9141"
  },
  {
    "period": "2018.12.14",
    "index": "31.4863"
  },
  {
    "period": "2018.12.15",
    "index": "28.3187"
  },
  {
    "period": "2018.12.16",
    "index": "34.0769"
  },
  {
    "period": "2018.12.17",
    "index": "39.5724"
  },
  {
    "period": "2018.12.18",
    "index": "37.7222"
  },
  {
    "period": "2018.12.19",
    "index": "36.8328"
  },
  {
    "period": "2018.12.20",
    "index": "33.8164"
  },
  {
    "period": "2018.12.21",
    "index": "28.0627"
  },
  {
    "period": "2018.12.22",
    "index": "26.5308"
  },
  {
    "period": "2018.12.23",
    "index": "29.4573"
  },
  {
    "period": "2018.12.24",
    "index": "26.966"
  },
  {
    "period": "2018.12.25",
    "index": "30.6542"
  },
  {
    "period": "2018.12.26",
    "index": "35.5759"
  },
  {
    "period": "2018.12.27",
    "index": "33.4471"
  },
  {
    "period": "2018.12.28",
    "index": "29.8447"
  },
  {
    "period": "2018.12.29",
    "index": "27.5006"
  },
  {
    "period": "2018.12.30",
    "index": "30.1946"
  },
  {
    "period": "2018.12.31",
    "index": "26.8256"
  },
  {
    "period": "2019.1.1",
    "index": "33.4132"
  },
  {
    "period": "2019.1.2",
    "index": "42.4213"
  },
  {
    "period": "2019.1.3",
    "index": "40.1666"
  },
  {
    "period": "2019.1.4",
    "index": "36.161"
  },
  {
    "period": "2019.1.5",
    "index": "33.3229"
  },
  {
    "period": "2019.1.6",
    "index": "39.9684"
  },
  {
    "period": "2019.1.7",
    "index": "43.7884"
  },
  {
    "period": "2019.1.8",
    "index": "43.1744"
  },
  {
    "period": "2019.1.9",
    "index": "42.6218"
  },
  {
    "period": "2019.1.10",
    "index": "39.0379"
  },
  {
    "period": "2019.1.11",
    "index": "32.4863"
  },
  {
    "period": "2019.1.12",
    "index": "29.0677"
  },
  {
    "period": "2019.1.13",
    "index": "35.4671"
  },
  {
    "period": "2019.1.14",
    "index": "39.9196"
  },
  {
    "period": "2019.1.15",
    "index": "39.2419"
  },
  {
    "period": "2019.1.16",
    "index": "39.0099"
  },
  {
    "period": "2019.1.17",
    "index": "39.2103"
  },
  {
    "period": "2019.1.18",
    "index": "33.9984"
  },
  {
    "period": "2019.1.19",
    "index": "31.4746"
  },
  {
    "period": "2019.1.20",
    "index": "40.8018"
  },
  {
    "period": "2019.1.21",
    "index": "43.0769"
  },
  {
    "period": "2019.1.22",
    "index": "43.1198"
  },
  {
    "period": "2019.1.23",
    "index": "42.5942"
  },
  {
    "period": "2019.1.24",
    "index": "39.7011"
  },
  {
    "period": "2019.1.25",
    "index": "35.1614"
  },
  {
    "period": "2019.1.26",
    "index": "32.1066"
  },
  {
    "period": "2019.1.27",
    "index": "38.4099"
  },
  {
    "period": "2019.1.28",
    "index": "42.1121"
  },
  {
    "period": "2019.1.29",
    "index": "38.2116"
  },
  {
    "period": "2019.1.30",
    "index": "34.8526"
  },
  {
    "period": "2019.1.31",
    "index": "30.2546"
  },
  {
    "period": "2019.2.1",
    "index": "27.1795"
  },
  {
    "period": "2019.2.2",
    "index": "24.7171"
  },
  {
    "period": "2019.2.3",
    "index": "26.8911"
  },
  {
    "period": "2019.2.4",
    "index": "23.3153"
  },
  {
    "period": "2019.2.5",
    "index": "24.8232"
  },
  {
    "period": "2019.2.6",
    "index": "38.0866"
  },
  {
    "period": "2019.2.7",
    "index": "45.5492"
  },
  {
    "period": "2019.2.8",
    "index": "43.6832"
  },
  {
    "period": "2019.2.9",
    "index": "40.5883"
  },
  {
    "period": "2019.2.10",
    "index": "46.7683"
  },
  {
    "period": "2019.2.11",
    "index": "47.9882"
  },
  {
    "period": "2019.2.12",
    "index": "46.319"
  },
  {
    "period": "2019.2.13",
    "index": "44.7808"
  },
  {
    "period": "2019.2.14",
    "index": "40.9265"
  },
  {
    "period": "2019.2.15",
    "index": "39.0343"
  },
  {
    "period": "2019.2.16",
    "index": "35.7646"
  },
  {
    "period": "2019.2.17",
    "index": "42.3229"
  },
  {
    "period": "2019.2.18",
    "index": "47.0671"
  },
  {
    "period": "2019.2.19",
    "index": "45.3885"
  },
  {
    "period": "2019.2.20",
    "index": "43.9135"
  },
  {
    "period": "2019.2.21",
    "index": "40.9833"
  },
  {
    "period": "2019.2.22",
    "index": "38.4843"
  },
  {
    "period": "2019.2.23",
    "index": "36.2233"
  },
  {
    "period": "2019.2.24",
    "index": "44.8273"
  },
  {
    "period": "2019.2.25",
    "index": "47.7733"
  },
  {
    "period": "2019.2.26",
    "index": "46.5533"
  },
  {
    "period": "2019.2.27",
    "index": "46.7624"
  },
  {
    "period": "2019.2.28",
    "index": "39.4682"
  },
  {
    "period": "2019.3.1",
    "index": "38.4044"
  },
  {
    "period": "2019.3.2",
    "index": "40.3002"
  },
  {
    "period": "2019.3.3",
    "index": "47.6234"
  },
  {
    "period": "2019.3.4",
    "index": "51.852"
  },
  {
    "period": "2019.3.5",
    "index": "52.8209"
  },
  {
    "period": "2019.3.6",
    "index": "50.3102"
  },
  {
    "period": "2019.3.7",
    "index": "46.3917"
  },
  {
    "period": "2019.3.8",
    "index": "40.1937"
  },
  {
    "period": "2019.3.9",
    "index": "35.793"
  },
  {
    "period": "2019.3.10",
    "index": "43.6543"
  },
  {
    "period": "2019.3.11",
    "index": "47.8256"
  },
  {
    "period": "2019.3.12",
    "index": "44.4932"
  },
  {
    "period": "2019.3.13",
    "index": "42.6213"
  },
  {
    "period": "2019.3.14",
    "index": "40.0695"
  },
  {
    "period": "2019.3.15",
    "index": "36.6667"
  },
  {
    "period": "2019.3.16",
    "index": "35.1668"
  },
  {
    "period": "2019.3.17",
    "index": "40.8917"
  },
  {
    "period": "2019.3.18",
    "index": "46.3086"
  },
  {
    "period": "2019.3.19",
    "index": "46.6874"
  },
  {
    "period": "2019.3.20",
    "index": "45.1402"
  },
  {
    "period": "2019.3.21",
    "index": "42.62"
  },
  {
    "period": "2019.3.22",
    "index": "38.893"
  },
  {
    "period": "2019.3.23",
    "index": "33.9045"
  },
  {
    "period": "2019.3.24",
    "index": "45.3406"
  },
  {
    "period": "2019.3.25",
    "index": "50.0316"
  },
  {
    "period": "2019.3.26",
    "index": "46.3682"
  },
  {
    "period": "2019.3.27",
    "index": "44.6101"
  },
  {
    "period": "2019.3.28",
    "index": "41.4556"
  },
  {
    "period": "2019.3.29",
    "index": "35.4196"
  },
  {
    "period": "2019.3.30",
    "index": "34.9027"
  },
  {
    "period": "2019.3.31",
    "index": "41.2958"
  },
  {
    "period": "2019.4.1",
    "index": "48.5602"
  },
  {
    "period": "2019.4.2",
    "index": "51.0452"
  },
  {
    "period": "2019.4.3",
    "index": "49.6551"
  },
  {
    "period": "2019.4.4",
    "index": "46.2513"
  },
  {
    "period": "2019.4.5",
    "index": "38.8117"
  },
  {
    "period": "2019.4.6",
    "index": "35.9244"
  },
  {
    "period": "2019.4.7",
    "index": "42.736"
  },
  {
    "period": "2019.4.8",
    "index": "52.0479"
  },
  {
    "period": "2019.4.9",
    "index": "49.8199"
  },
  {
    "period": "2019.4.10",
    "index": "49.6993"
  },
  {
    "period": "2019.4.11",
    "index": "45.9619"
  },
  {
    "period": "2019.4.12",
    "index": "40.3485"
  },
  {
    "period": "2019.4.13",
    "index": "36.8071"
  },
  {
    "period": "2019.4.14",
    "index": "50.6772"
  },
  {
    "period": "2019.4.15",
    "index": "52.9013"
  },
  {
    "period": "2019.4.16",
    "index": "49.7743"
  },
  {
    "period": "2019.4.17",
    "index": "53.4566"
  },
  {
    "period": "2019.4.18",
    "index": "47.8396"
  },
  {
    "period": "2019.4.19",
    "index": "42.6295"
  },
  {
    "period": "2019.4.20",
    "index": "36.7073"
  },
  {
    "period": "2019.4.21",
    "index": "44.5975"
  },
  {
    "period": "2019.4.22",
    "index": "54.0666"
  },
  {
    "period": "2019.4.23",
    "index": "52.6489"
  },
  {
    "period": "2019.4.24",
    "index": "50.9346"
  },
  {
    "period": "2019.4.25",
    "index": "49.269"
  },
  {
    "period": "2019.4.26",
    "index": "42.8457"
  },
  {
    "period": "2019.4.27",
    "index": "33.5686"
  },
  {
    "period": "2019.4.28",
    "index": "40.8524"
  },
  {
    "period": "2019.4.29",
    "index": "51.3445"
  },
  {
    "period": "2019.4.30",
    "index": "43.9121"
  },
  {
    "period": "2019.5.1",
    "index": "44.2824"
  },
  {
    "period": "2019.5.2",
    "index": "46.4825"
  },
  {
    "period": "2019.5.3",
    "index": "39.7986"
  },
  {
    "period": "2019.5.4",
    "index": "32.5161"
  },
  {
    "period": "2019.5.5",
    "index": "34.7718"
  },
  {
    "period": "2019.5.6",
    "index": "46.5746"
  },
  {
    "period": "2019.5.7",
    "index": "51.1554"
  },
  {
    "period": "2019.5.8",
    "index": "50.5133"
  },
  {
    "period": "2019.5.9",
    "index": "48.869"
  },
  {
    "period": "2019.5.10",
    "index": "43.8661"
  },
  {
    "period": "2019.5.11",
    "index": "38.1281"
  },
  {
    "period": "2019.5.12",
    "index": "47.1398"
  },
  {
    "period": "2019.5.13",
    "index": "55.1217"
  },
  {
    "period": "2019.5.14",
    "index": "54.1578"
  },
  {
    "period": "2019.5.15",
    "index": "54.3799"
  },
  {
    "period": "2019.5.16",
    "index": "55.8553"
  },
  {
    "period": "2019.5.17",
    "index": "46.7285"
  },
  {
    "period": "2019.5.18",
    "index": "39.7481"
  },
  {
    "period": "2019.5.19",
    "index": "50.7833"
  },
  {
    "period": "2019.5.20",
    "index": "56.0305"
  },
  {
    "period": "2019.5.21",
    "index": "53.3464"
  },
  {
    "period": "2019.5.22",
    "index": "54.6178"
  },
  {
    "period": "2019.5.23",
    "index": "54.6386"
  },
  {
    "period": "2019.5.24",
    "index": "48.9566"
  },
  {
    "period": "2019.5.25",
    "index": "41.4795"
  },
  {
    "period": "2019.5.26",
    "index": "50.6971"
  },
  {
    "period": "2019.5.27",
    "index": "59.5688"
  },
  {
    "period": "2019.5.28",
    "index": "56.1624"
  },
  {
    "period": "2019.5.29",
    "index": "56.8911"
  },
  {
    "period": "2019.5.30",
    "index": "53.052"
  },
  {
    "period": "2019.5.31",
    "index": "44.2855"
  },
  {
    "period": "2019.6.1",
    "index": "41.7996"
  },
  {
    "period": "2019.6.2",
    "index": "50.6556"
  },
  {
    "period": "2019.6.3",
    "index": "59.9986"
  },
  {
    "period": "2019.6.4",
    "index": "61.1712"
  },
  {
    "period": "2019.6.5",
    "index": "53.2642"
  },
  {
    "period": "2019.6.6",
    "index": "51.8439"
  },
  {
    "period": "2019.6.7",
    "index": "50.1056"
  },
  {
    "period": "2019.6.8",
    "index": "42.7884"
  },
  {
    "period": "2019.6.9",
    "index": "53.8679"
  },
  {
    "period": "2019.6.10",
    "index": "59.5909"
  },
  {
    "period": "2019.6.11",
    "index": "60.163"
  },
  {
    "period": "2019.6.12",
    "index": "59.2388"
  },
  {
    "period": "2019.6.13",
    "index": "56.7953"
  },
  {
    "period": "2019.6.14",
    "index": "49.4596"
  },
  {
    "period": "2019.6.15",
    "index": "44.8774"
  },
  {
    "period": "2019.6.16",
    "index": "54.607"
  },
  {
    "period": "2019.6.17",
    "index": "63.2787"
  },
  {
    "period": "2019.6.18",
    "index": "62.4493"
  },
  {
    "period": "2019.6.19",
    "index": "59.0744"
  },
  {
    "period": "2019.6.20",
    "index": "56.8251"
  },
  {
    "period": "2019.6.21",
    "index": "51.4899"
  },
  {
    "period": "2019.6.22",
    "index": "42.3933"
  },
  {
    "period": "2019.6.23",
    "index": "50.8113"
  },
  {
    "period": "2019.6.24",
    "index": "62.5613"
  },
  {
    "period": "2019.6.25",
    "index": "60.6217"
  },
  {
    "period": "2019.6.26",
    "index": "57.5696"
  },
  {
    "period": "2019.6.27",
    "index": "52.1884"
  },
  {
    "period": "2019.6.28",
    "index": "46.8292"
  },
  {
    "period": "2019.6.29",
    "index": "44.7487"
  },
  {
    "period": "2019.6.30",
    "index": "52.955"
  },
  {
    "period": "2019.7.1",
    "index": "61.7725"
  },
  {
    "period": "2019.7.2",
    "index": "59.7273"
  },
  {
    "period": "2019.7.3",
    "index": "59.8578"
  },
  {
    "period": "2019.7.4",
    "index": "58.897"
  },
  {
    "period": "2019.7.5",
    "index": "51.8168"
  },
  {
    "period": "2019.7.6",
    "index": "44.3821"
  },
  {
    "period": "2019.7.7",
    "index": "54.0611"
  },
  {
    "period": "2019.7.8",
    "index": "62.9283"
  },
  {
    "period": "2019.7.9",
    "index": "61.871"
  },
  {
    "period": "2019.7.10",
    "index": "57.7629"
  },
  {
    "period": "2019.7.11",
    "index": "53.1568"
  },
  {
    "period": "2019.7.12",
    "index": "45.8382"
  },
  {
    "period": "2019.7.13",
    "index": "42.7843"
  },
  {
    "period": "2019.7.14",
    "index": "52.7369"
  },
  {
    "period": "2019.7.15",
    "index": "60.042"
  },
  {
    "period": "2019.7.16",
    "index": "60.9526"
  },
  {
    "period": "2019.7.17",
    "index": "58.9674"
  },
  {
    "period": "2019.7.18",
    "index": "54.7004"
  },
  {
    "period": "2019.7.19",
    "index": "47.766"
  },
  {
    "period": "2019.7.20",
    "index": "44.8616"
  },
  {
    "period": "2019.7.21",
    "index": "55.4635"
  },
  {
    "period": "2019.7.22",
    "index": "61.489"
  },
  {
    "period": "2019.7.23",
    "index": "60.3445"
  },
  {
    "period": "2019.7.24",
    "index": "58.925"
  },
  {
    "period": "2019.7.25",
    "index": "55.1601"
  },
  {
    "period": "2019.7.26",
    "index": "49.2144"
  },
  {
    "period": "2019.7.27",
    "index": "41.4809"
  },
  {
    "period": "2019.7.28",
    "index": "51.8041"
  },
  {
    "period": "2019.7.29",
    "index": "56.8712"
  },
  {
    "period": "2019.7.30",
    "index": "54.6147"
  },
  {
    "period": "2019.7.31",
    "index": "52.8295"
  },
  {
    "period": "2019.8.1",
    "index": "51.4375"
  },
  {
    "period": "2019.8.2",
    "index": "46.4956"
  },
  {
    "period": "2019.8.3",
    "index": "43.0931"
  },
  {
    "period": "2019.8.4",
    "index": "52.1197"
  },
  {
    "period": "2019.8.5",
    "index": "58.7403"
  },
  {
    "period": "2019.8.6",
    "index": "59.2957"
  },
  {
    "period": "2019.8.7",
    "index": "57.85"
  },
  {
    "period": "2019.8.8",
    "index": "54.5392"
  },
  {
    "period": "2019.8.9",
    "index": "48.0897"
  },
  {
    "period": "2019.8.10",
    "index": "45.2806"
  },
  {
    "period": "2019.8.11",
    "index": "52.9428"
  },
  {
    "period": "2019.8.12",
    "index": "60.0194"
  },
  {
    "period": "2019.8.13",
    "index": "60.4158"
  },
  {
    "period": "2019.8.14",
    "index": "50.8786"
  },
  {
    "period": "2019.8.15",
    "index": "50.4926"
  },
  {
    "period": "2019.8.16",
    "index": "50.7806"
  },
  {
    "period": "2019.8.17",
    "index": "45.6436"
  },
  {
    "period": "2019.8.18",
    "index": "52.3681"
  },
  {
    "period": "2019.8.19",
    "index": "57.8762"
  },
  {
    "period": "2019.8.20",
    "index": "57.0595"
  },
  {
    "period": "2019.8.21",
    "index": "56.7276"
  },
  {
    "period": "2019.8.22",
    "index": "53.3934"
  },
  {
    "period": "2019.8.23",
    "index": "46.85"
  },
  {
    "period": "2019.8.24",
    "index": "42.0538"
  },
  {
    "period": "2019.8.25",
    "index": "47.9051"
  },
  {
    "period": "2019.8.26",
    "index": "58.0198"
  },
  {
    "period": "2019.8.27",
    "index": "58.9972"
  },
  {
    "period": "2019.8.28",
    "index": "58.7665"
  },
  {
    "period": "2019.8.29",
    "index": "55.5063"
  },
  {
    "period": "2019.8.30",
    "index": "44.5961"
  },
  {
    "period": "2019.8.31",
    "index": "40.4853"
  },
  {
    "period": "2019.9.1",
    "index": "52.9599"
  },
  {
    "period": "2019.9.2",
    "index": "60.107"
  },
  {
    "period": "2019.9.3",
    "index": "58.776"
  },
  {
    "period": "2019.9.4",
    "index": "55.9506"
  },
  {
    "period": "2019.9.5",
    "index": "51.7996"
  },
  {
    "period": "2019.9.6",
    "index": "42.9243"
  },
  {
    "period": "2019.9.7",
    "index": "41.0646"
  },
  {
    "period": "2019.9.8",
    "index": "44.5605"
  },
  {
    "period": "2019.9.9",
    "index": "46.1944"
  },
  {
    "period": "2019.9.10",
    "index": "39.7901"
  },
  {
    "period": "2019.9.11",
    "index": "32.7554"
  },
  {
    "period": "2019.9.12",
    "index": "28.1241"
  },
  {
    "period": "2019.9.13",
    "index": "30.7562"
  },
  {
    "period": "2019.9.14",
    "index": "41.5039"
  },
  {
    "period": "2019.9.15",
    "index": "56.2892"
  },
  {
    "period": "2019.9.16",
    "index": "64.067"
  },
  {
    "period": "2019.9.17",
    "index": "62.3942"
  },
  {
    "period": "2019.9.18",
    "index": "58.3674"
  },
  {
    "period": "2019.9.19",
    "index": "53.4895"
  },
  {
    "period": "2019.9.20",
    "index": "46.0824"
  },
  {
    "period": "2019.9.21",
    "index": "44.2517"
  },
  {
    "period": "2019.9.22",
    "index": "52.8642"
  },
  {
    "period": "2019.9.23",
    "index": "58.3232"
  },
  {
    "period": "2019.9.24",
    "index": "56.985"
  },
  {
    "period": "2019.9.25",
    "index": "54.1501"
  },
  {
    "period": "2019.9.26",
    "index": "50.0348"
  },
  {
    "period": "2019.9.27",
    "index": "45.4282"
  },
  {
    "period": "2019.9.28",
    "index": "39.3033"
  },
  {
    "period": "2019.9.29",
    "index": "49.0167"
  },
  {
    "period": "2019.9.30",
    "index": "58.1796"
  },
  {
    "period": "2019.10.1",
    "index": "56.152"
  },
  {
    "period": "2019.10.2",
    "index": "52.3202"
  },
  {
    "period": "2019.10.3",
    "index": "47.147"
  },
  {
    "period": "2019.10.4",
    "index": "45.9154"
  },
  {
    "period": "2019.10.5",
    "index": "41.1897"
  },
  {
    "period": "2019.10.6",
    "index": "50.4203"
  },
  {
    "period": "2019.10.7",
    "index": "58.204"
  },
  {
    "period": "2019.10.8",
    "index": "49.2103"
  },
  {
    "period": "2019.10.9",
    "index": "49.7169"
  },
  {
    "period": "2019.10.10",
    "index": "53.6652"
  },
  {
    "period": "2019.10.11",
    "index": "46.2955"
  },
  {
    "period": "2019.10.12",
    "index": "41.5942"
  },
  {
    "period": "2019.10.13",
    "index": "48.9065"
  },
  {
    "period": "2019.10.14",
    "index": "57.6897"
  },
  {
    "period": "2019.10.15",
    "index": "56.2843"
  },
  {
    "period": "2019.10.16",
    "index": "53.4877"
  },
  {
    "period": "2019.10.17",
    "index": "51.2565"
  },
  {
    "period": "2019.10.18",
    "index": "45.7091"
  },
  {
    "period": "2019.10.19",
    "index": "37.7231"
  },
  {
    "period": "2019.10.20",
    "index": "47.6459"
  },
  {
    "period": "2019.10.21",
    "index": "56.4748"
  },
  {
    "period": "2019.10.22",
    "index": "55.1185"
  },
  {
    "period": "2019.10.23",
    "index": "52.1197"
  },
  {
    "period": "2019.10.24",
    "index": "48.6419"
  },
  {
    "period": "2019.10.25",
    "index": "42.0258"
  },
  {
    "period": "2019.10.26",
    "index": "37.371"
  },
  {
    "period": "2019.10.27",
    "index": "46.9809"
  },
  {
    "period": "2019.10.28",
    "index": "54.6995"
  },
  {
    "period": "2019.10.29",
    "index": "54.8034"
  },
  {
    "period": "2019.10.30",
    "index": "51.5739"
  },
  {
    "period": "2019.10.31",
    "index": "47.082"
  },
  {
    "period": "2019.11.1",
    "index": "44.9027"
  },
  {
    "period": "2019.11.2",
    "index": "42.5798"
  },
  {
    "period": "2019.11.3",
    "index": "54.6408"
  },
  {
    "period": "2019.11.4",
    "index": "63.2178"
  },
  {
    "period": "2019.11.5",
    "index": "59.7196"
  },
  {
    "period": "2019.11.6",
    "index": "64.5627"
  },
  {
    "period": "2019.11.7",
    "index": "55.3271"
  },
  {
    "period": "2019.11.8",
    "index": "48.8537"
  },
  {
    "period": "2019.11.9",
    "index": "43.7397"
  },
  {
    "period": "2019.11.10",
    "index": "53.2769"
  },
  {
    "period": "2019.11.11",
    "index": "60.7124"
  },
  {
    "period": "2019.11.12",
    "index": "58.7214"
  },
  {
    "period": "2019.11.13",
    "index": "56.1267"
  },
  {
    "period": "2019.11.14",
    "index": "50.1409"
  },
  {
    "period": "2019.11.15",
    "index": "43.2949"
  },
  {
    "period": "2019.11.16",
    "index": "39.2027"
  },
  {
    "period": "2019.11.17",
    "index": "49.7043"
  },
  {
    "period": "2019.11.18",
    "index": "57.3051"
  },
  {
    "period": "2019.11.19",
    "index": "54.6485"
  },
  {
    "period": "2019.11.20",
    "index": "51.0967"
  },
  {
    "period": "2019.11.21",
    "index": "47.1827"
  },
  {
    "period": "2019.11.22",
    "index": "41.6881"
  },
  {
    "period": "2019.11.23",
    "index": "37.6432"
  },
  {
    "period": "2019.11.24",
    "index": "46.9267"
  },
  {
    "period": "2019.11.25",
    "index": "53.4159"
  },
  {
    "period": "2019.11.26",
    "index": "53.4683"
  },
  {
    "period": "2019.11.27",
    "index": "51.764"
  },
  {
    "period": "2019.11.28",
    "index": "47.4161"
  },
  {
    "period": "2019.11.29",
    "index": "39.604"
  },
  {
    "period": "2019.11.30",
    "index": "36.3903"
  },
  {
    "period": "2019.12.1",
    "index": "48.3173"
  },
  {
    "period": "2019.12.2",
    "index": "56.771"
  },
  {
    "period": "2019.12.3",
    "index": "51.3852"
  },
  {
    "period": "2019.12.4",
    "index": "49.0794"
  },
  {
    "period": "2019.12.5",
    "index": "47.3543"
  },
  {
    "period": "2019.12.6",
    "index": "41.4479"
  },
  {
    "period": "2019.12.7",
    "index": "36.7059"
  },
  {
    "period": "2019.12.8",
    "index": "43.676"
  },
  {
    "period": "2019.12.9",
    "index": "50.1291"
  },
  {
    "period": "2019.12.10",
    "index": "48.8555"
  },
  {
    "period": "2019.12.11",
    "index": "49.9553"
  },
  {
    "period": "2019.12.12",
    "index": "45.6562"
  },
  {
    "period": "2019.12.13",
    "index": "40.1797"
  },
  {
    "period": "2019.12.14",
    "index": "36.0842"
  },
  {
    "period": "2019.12.15",
    "index": "43.2385"
  },
  {
    "period": "2019.12.16",
    "index": "50.0492"
  },
  {
    "period": "2019.12.17",
    "index": "47.4586"
  },
  {
    "period": "2019.12.18",
    "index": "43.2259"
  },
  {
    "period": "2019.12.19",
    "index": "40.279"
  },
  {
    "period": "2019.12.20",
    "index": "34.979"
  },
  {
    "period": "2019.12.21",
    "index": "32.5893"
  },
  {
    "period": "2019.12.22",
    "index": "37.4726"
  },
  {
    "period": "2019.12.23",
    "index": "40.3052"
  },
  {
    "period": "2019.12.24",
    "index": "31.661"
  },
  {
    "period": "2019.12.25",
    "index": "34.0665"
  },
  {
    "period": "2019.12.26",
    "index": "38.9087"
  },
  {
    "period": "2019.12.27",
    "index": "34.4151"
  },
  {
    "period": "2019.12.28",
    "index": "31.5468"
  },
  {
    "period": "2019.12.29",
    "index": "39.1169"
  },
  {
    "period": "2019.12.30",
    "index": "39.4478"
  },
  {
    "period": "2019.12.31",
    "index": "31.6533"
  },
  {
    "period": "2020.1.1",
    "index": "38.6288"
  },
  {
    "period": "2020.1.2",
    "index": "45.4756"
  },
  {
    "period": "2020.1.3",
    "index": "39.814"
  },
  {
    "period": "2020.1.4",
    "index": "37.6771"
  },
  {
    "period": "2020.1.5",
    "index": "45.2296"
  },
  {
    "period": "2020.1.6",
    "index": "48.7575"
  },
  {
    "period": "2020.1.7",
    "index": "47.9548"
  },
  {
    "period": "2020.1.8",
    "index": "46.4874"
  },
  {
    "period": "2020.1.9",
    "index": "44.3794"
  },
  {
    "period": "2020.1.10",
    "index": "39.6803"
  },
  {
    "period": "2020.1.11",
    "index": "36.7773"
  },
  {
    "period": "2020.1.12",
    "index": "42.1419"
  },
  {
    "period": "2020.1.13",
    "index": "48.2229"
  },
  {
    "period": "2020.1.14",
    "index": "46.6676"
  },
  {
    "period": "2020.1.15",
    "index": "44.7275"
  },
  {
    "period": "2020.1.16",
    "index": "42.2123"
  },
  {
    "period": "2020.1.17",
    "index": "36.9949"
  },
  {
    "period": "2020.1.18",
    "index": "34.6765"
  },
  {
    "period": "2020.1.19",
    "index": "41.3901"
  },
  {
    "period": "2020.1.20",
    "index": "41.1563"
  },
  {
    "period": "2020.1.21",
    "index": "37.4134"
  },
  {
    "period": "2020.1.22",
    "index": "33.4629"
  },
  {
    "period": "2020.1.23",
    "index": "26.9809"
  },
  {
    "period": "2020.1.24",
    "index": "24.0693"
  },
  {
    "period": "2020.1.25",
    "index": "25.1099"
  },
  {
    "period": "2020.1.26",
    "index": "32.1157"
  },
  {
    "period": "2020.1.27",
    "index": "44.7736"
  },
  {
    "period": "2020.1.28",
    "index": "46.6743"
  },
  {
    "period": "2020.1.29",
    "index": "47.5227"
  },
  {
    "period": "2020.1.30",
    "index": "46.2427"
  },
  {
    "period": "2020.1.31",
    "index": "40.0357"
  },
  {
    "period": "2020.2.1",
    "index": "43.3392"
  },
  {
    "period": "2020.2.2",
    "index": "52.1143"
  },
  {
    "period": "2020.2.3",
    "index": "50.0953"
  },
  {
    "period": "2020.2.4",
    "index": "58.7173"
  },
  {
    "period": "2020.2.5",
    "index": "53.6042"
  },
  {
    "period": "2020.2.6",
    "index": "49.9937"
  },
  {
    "period": "2020.2.7",
    "index": "43.7013"
  },
  {
    "period": "2020.2.8",
    "index": "42.8453"
  },
  {
    "period": "2020.2.9",
    "index": "52.9595"
  },
  {
    "period": "2020.2.10",
    "index": "53.1965"
  },
  {
    "period": "2020.2.11",
    "index": "54.7971"
  },
  {
    "period": "2020.2.12",
    "index": "57.4802"
  },
  {
    "period": "2020.2.13",
    "index": "53.4534"
  },
  {
    "period": "2020.2.14",
    "index": "45.6969"
  },
  {
    "period": "2020.2.15",
    "index": "44.9384"
  },
  {
    "period": "2020.2.16",
    "index": "52.2236"
  },
  {
    "period": "2020.2.17",
    "index": "56.8364"
  },
  {
    "period": "2020.2.18",
    "index": "55.3447"
  },
  {
    "period": "2020.2.19",
    "index": "53.5329"
  },
  {
    "period": "2020.2.20",
    "index": "49.4623"
  },
  {
    "period": "2020.2.21",
    "index": "43.3532"
  },
  {
    "period": "2020.2.22",
    "index": "44.718"
  },
  {
    "period": "2020.2.23",
    "index": "49.893"
  },
  {
    "period": "2020.2.24",
    "index": "54.3988"
  },
  {
    "period": "2020.2.25",
    "index": "57.5963"
  },
  {
    "period": "2020.2.26",
    "index": "58.9115"
  },
  {
    "period": "2020.2.27",
    "index": "57.5218"
  },
  {
    "period": "2020.2.28",
    "index": "53.858"
  },
  {
    "period": "2020.2.29",
    "index": "55.509"
  },
  {
    "period": "2020.3.1",
    "index": "66.7488"
  },
  {
    "period": "2020.3.2",
    "index": "66.3438"
  },
  {
    "period": "2020.3.3",
    "index": "69.1137"
  },
  {
    "period": "2020.3.4",
    "index": "68.8081"
  },
  {
    "period": "2020.3.5",
    "index": "63.6701"
  },
  {
    "period": "2020.3.6",
    "index": "57.1385"
  },
  {
    "period": "2020.3.7",
    "index": "60.3445"
  },
  {
    "period": "2020.3.8",
    "index": "66.3773"
  },
  {
    "period": "2020.3.9",
    "index": "72.303"
  },
  {
    "period": "2020.3.10",
    "index": "70.2673"
  },
  {
    "period": "2020.3.11",
    "index": "69.3106"
  },
  {
    "period": "2020.3.12",
    "index": "67.4947"
  },
  {
    "period": "2020.3.13",
    "index": "57.6076"
  },
  {
    "period": "2020.3.14",
    "index": "57.8243"
  },
  {
    "period": "2020.3.15",
    "index": "68.2518"
  },
  {
    "period": "2020.3.16",
    "index": "71.9382"
  },
  {
    "period": "2020.3.17",
    "index": "69.1223"
  },
  {
    "period": "2020.3.18",
    "index": "66.1186"
  },
  {
    "period": "2020.3.19",
    "index": "64.7244"
  },
  {
    "period": "2020.3.20",
    "index": "56.4906"
  },
  {
    "period": "2020.3.21",
    "index": "55.3253"
  },
  {
    "period": "2020.3.22",
    "index": "63.3252"
  },
  {
    "period": "2020.3.23",
    "index": "68.8185"
  },
  {
    "period": "2020.3.24",
    "index": "66.9552"
  },
  {
    "period": "2020.3.25",
    "index": "64.6052"
  },
  {
    "period": "2020.3.26",
    "index": "64.397"
  },
  {
    "period": "2020.3.27",
    "index": "57.6825"
  },
  {
    "period": "2020.3.28",
    "index": "55.263"
  },
  {
    "period": "2020.3.29",
    "index": "62.0687"
  },
  {
    "period": "2020.3.30",
    "index": "68.4112"
  },
  {
    "period": "2020.3.31",
    "index": "69.0081"
  },
  {
    "period": "2020.4.1",
    "index": "68.7571"
  },
  {
    "period": "2020.4.2",
    "index": "69.3043"
  },
  {
    "period": "2020.4.3",
    "index": "58.832"
  },
  {
    "period": "2020.4.4",
    "index": "57.4843"
  },
  {
    "period": "2020.4.5",
    "index": "70.9161"
  },
  {
    "period": "2020.4.6",
    "index": "75.7614"
  },
  {
    "period": "2020.4.7",
    "index": "74.0823"
  },
  {
    "period": "2020.4.8",
    "index": "72.3581"
  },
  {
    "period": "2020.4.9",
    "index": "68.5304"
  },
  {
    "period": "2020.4.10",
    "index": "59.4234"
  },
  {
    "period": "2020.4.11",
    "index": "59.1237"
  },
  {
    "period": "2020.4.12",
    "index": "75.4188"
  },
  {
    "period": "2020.4.13",
    "index": "73.6295"
  },
  {
    "period": "2020.4.14",
    "index": "69.4966"
  },
  {
    "period": "2020.4.15",
    "index": "70.651"
  },
  {
    "period": "2020.4.16",
    "index": "73.3573"
  },
  {
    "period": "2020.4.17",
    "index": "68.5363"
  },
  {
    "period": "2020.4.18",
    "index": "62.303"
  },
  {
    "period": "2020.4.19",
    "index": "80.5413"
  },
  {
    "period": "2020.4.20",
    "index": "79.1494"
  },
  {
    "period": "2020.4.21",
    "index": "80.1991"
  },
  {
    "period": "2020.4.22",
    "index": "81.1219"
  },
  {
    "period": "2020.4.23",
    "index": "73.383"
  },
  {
    "period": "2020.4.24",
    "index": "62.4972"
  },
  {
    "period": "2020.4.25",
    "index": "60.4465"
  },
  {
    "period": "2020.4.26",
    "index": "72.4579"
  },
  {
    "period": "2020.4.27",
    "index": "77.9322"
  },
  {
    "period": "2020.4.28",
    "index": "69.316"
  },
  {
    "period": "2020.4.29",
    "index": "59.8429"
  },
  {
    "period": "2020.4.30",
    "index": "58.0189"
  },
  {
    "period": "2020.5.1",
    "index": "58.8094"
  },
  {
    "period": "2020.5.2",
    "index": "57.613"
  },
  {
    "period": "2020.5.3",
    "index": "69.4113"
  },
  {
    "period": "2020.5.4",
    "index": "66.8784"
  },
  {
    "period": "2020.5.5",
    "index": "77.3593"
  },
  {
    "period": "2020.5.6",
    "index": "77.715"
  },
  {
    "period": "2020.5.7",
    "index": "71.2393"
  },
  {
    "period": "2020.5.8",
    "index": "58.376"
  },
  {
    "period": "2020.5.9",
    "index": "62.6999"
  },
  {
    "period": "2020.5.10",
    "index": "72.2484"
  },
  {
    "period": "2020.5.11",
    "index": "76.2414"
  },
  {
    "period": "2020.5.12",
    "index": "75.5384"
  },
  {
    "period": "2020.5.13",
    "index": "71.9315"
  },
  {
    "period": "2020.5.14",
    "index": "70.4221"
  },
  {
    "period": "2020.5.15",
    "index": "67.1014"
  },
  {
    "period": "2020.5.16",
    "index": "60.1725"
  },
  {
    "period": "2020.5.17",
    "index": "73.3211"
  },
  {
    "period": "2020.5.18",
    "index": "83.2498"
  },
  {
    "period": "2020.5.19",
    "index": "80.3901"
  },
  {
    "period": "2020.5.20",
    "index": "75.063"
  },
  {
    "period": "2020.5.21",
    "index": "73.3424"
  },
  {
    "period": "2020.5.22",
    "index": "67.7295"
  },
  {
    "period": "2020.5.23",
    "index": "65.6233"
  },
  {
    "period": "2020.5.24",
    "index": "82.9821"
  },
  {
    "period": "2020.5.25",
    "index": "93.0539"
  },
  {
    "period": "2020.5.26",
    "index": "92.1179"
  },
  {
    "period": "2020.5.27",
    "index": "90.4881"
  },
  {
    "period": "2020.5.28",
    "index": "81.6235"
  },
  {
    "period": "2020.5.29",
    "index": "71.8976"
  },
  {
    "period": "2020.5.30",
    "index": "68.5372"
  },
  {
    "period": "2020.5.31",
    "index": "86.422"
  },
  {
    "period": "2020.6.1",
    "index": "95.2978"
  },
  {
    "period": "2020.6.2",
    "index": "92.7509"
  },
  {
    "period": "2020.6.3",
    "index": "92.5861"
  },
  {
    "period": "2020.6.4",
    "index": "87.4374"
  },
  {
    "period": "2020.6.5",
    "index": "72.755"
  },
  {
    "period": "2020.6.6",
    "index": "69.9824"
  },
  {
    "period": "2020.6.7",
    "index": "90.1228"
  },
  {
    "period": "2020.6.8",
    "index": "98.0022"
  },
  {
    "period": "2020.6.9",
    "index": "96.1958"
  },
  {
    "period": "2020.6.10",
    "index": "90.2628"
  },
  {
    "period": "2020.6.11",
    "index": "84.4675"
  },
  {
    "period": "2020.6.12",
    "index": "71.4669"
  },
  {
    "period": "2020.6.13",
    "index": "69.1115"
  },
  {
    "period": "2020.6.14",
    "index": "82.8665"
  },
  {
    "period": "2020.6.15",
    "index": "88.5494"
  },
  {
    "period": "2020.6.16",
    "index": "85.9827"
  },
  {
    "period": "2020.6.17",
    "index": "79.5661"
  },
  {
    "period": "2020.6.18",
    "index": "76.8269"
  },
  {
    "period": "2020.6.19",
    "index": "65.1835"
  },
  {
    "period": "2020.6.20",
    "index": "61.5725"
  },
  {
    "period": "2020.6.21",
    "index": "77.9177"
  },
  {
    "period": "2020.6.22",
    "index": "86.4734"
  },
  {
    "period": "2020.6.23",
    "index": "81.9364"
  },
  {
    "period": "2020.6.24",
    "index": "80.9748"
  },
  {
    "period": "2020.6.25",
    "index": "72.2308"
  },
  {
    "period": "2020.6.26",
    "index": "64.1447"
  },
  {
    "period": "2020.6.27",
    "index": "61.0456"
  },
  {
    "period": "2020.6.28",
    "index": "77.2884"
  },
  {
    "period": "2020.6.29",
    "index": "80.3973"
  },
  {
    "period": "2020.6.30",
    "index": "79.9517"
  },
  {
    "period": "2020.7.1",
    "index": "74.6097"
  },
  {
    "period": "2020.7.2",
    "index": "73.8891"
  },
  {
    "period": "2020.7.3",
    "index": "66.0608"
  },
  {
    "period": "2020.7.4",
    "index": "58.7995"
  },
  {
    "period": "2020.7.5",
    "index": "76.3727"
  },
  {
    "period": "2020.7.6",
    "index": "83.183"
  },
  {
    "period": "2020.7.7",
    "index": "78.4293"
  },
  {
    "period": "2020.7.8",
    "index": "75.9384"
  },
  {
    "period": "2020.7.9",
    "index": "74.1893"
  },
  {
    "period": "2020.7.10",
    "index": "60.0632"
  },
  {
    "period": "2020.7.11",
    "index": "62.4037"
  },
  {
    "period": "2020.7.12",
    "index": "75.5488"
  },
  {
    "period": "2020.7.13",
    "index": "83.3934"
  },
  {
    "period": "2020.7.14",
    "index": "84.4431"
  },
  {
    "period": "2020.7.15",
    "index": "78.1426"
  },
  {
    "period": "2020.7.16",
    "index": "70.1874"
  },
  {
    "period": "2020.7.17",
    "index": "62.2475"
  },
  {
    "period": "2020.7.18",
    "index": "59.0577"
  },
  {
    "period": "2020.7.19",
    "index": "76.8793"
  },
  {
    "period": "2020.7.20",
    "index": "78.2568"
  },
  {
    "period": "2020.7.21",
    "index": "75.644"
  },
  {
    "period": "2020.7.22",
    "index": "76.4716"
  },
  {
    "period": "2020.7.23",
    "index": "73.8562"
  },
  {
    "period": "2020.7.24",
    "index": "61.7644"
  },
  {
    "period": "2020.7.25",
    "index": "58.4424"
  },
  {
    "period": "2020.7.26",
    "index": "71.3603"
  },
  {
    "period": "2020.7.27",
    "index": "77.1231"
  },
  {
    "period": "2020.7.28",
    "index": "75.0616"
  },
  {
    "period": "2020.7.29",
    "index": "70.9626"
  },
  {
    "period": "2020.7.30",
    "index": "64.1853"
  },
  {
    "period": "2020.7.31",
    "index": "57.324"
  },
  {
    "period": "2020.8.1",
    "index": "59.0329"
  },
  {
    "period": "2020.8.2",
    "index": "69.4131"
  },
  {
    "period": "2020.8.3",
    "index": "70.0266"
  },
  {
    "period": "2020.8.4",
    "index": "68.478"
  },
  {
    "period": "2020.8.5",
    "index": "69.269"
  },
  {
    "period": "2020.8.6",
    "index": "66.7308"
  },
  {
    "period": "2020.8.7",
    "index": "60.0858"
  },
  {
    "period": "2020.8.8",
    "index": "56.5804"
  },
  {
    "period": "2020.8.9",
    "index": "67.4265"
  },
  {
    "period": "2020.8.10",
    "index": "70.5314"
  },
  {
    "period": "2020.8.11",
    "index": "68.6491"
  },
  {
    "period": "2020.8.12",
    "index": "66.4472"
  },
  {
    "period": "2020.8.13",
    "index": "61.1829"
  },
  {
    "period": "2020.8.14",
    "index": "52.4597"
  },
  {
    "period": "2020.8.15",
    "index": "51.9292"
  },
  {
    "period": "2020.8.16",
    "index": "58.5286"
  },
  {
    "period": "2020.8.17",
    "index": "71.1901"
  },
  {
    "period": "2020.8.18",
    "index": "70.6208"
  },
  {
    "period": "2020.8.19",
    "index": "70.2736"
  },
  {
    "period": "2020.8.20",
    "index": "68.1335"
  },
  {
    "period": "2020.8.21",
    "index": "60.1838"
  },
  {
    "period": "2020.8.22",
    "index": "59.777"
  },
  {
    "period": "2020.8.23",
    "index": "70.4637"
  },
  {
    "period": "2020.8.24",
    "index": "72.9369"
  },
  {
    "period": "2020.8.25",
    "index": "76.4197"
  },
  {
    "period": "2020.8.26",
    "index": "74.7582"
  },
  {
    "period": "2020.8.27",
    "index": "72.9667"
  },
  {
    "period": "2020.8.28",
    "index": "64.7411"
  },
  {
    "period": "2020.8.29",
    "index": "67.092"
  },
  {
    "period": "2020.8.30",
    "index": "80.5147"
  },
  {
    "period": "2020.8.31",
    "index": "76.7863"
  },
  {
    "period": "2020.9.1",
    "index": "78.8772"
  },
  {
    "period": "2020.9.2",
    "index": "82.8475"
  },
  {
    "period": "2020.9.3",
    "index": "78.5015"
  },
  {
    "period": "2020.9.4",
    "index": "71.871"
  },
  {
    "period": "2020.9.5",
    "index": "73.7329"
  },
  {
    "period": "2020.9.6",
    "index": "91.8804"
  },
  {
    "period": "2020.9.7",
    "index": "97.6992"
  },
  {
    "period": "2020.9.8",
    "index": "98.7868"
  },
  {
    "period": "2020.9.9",
    "index": "78.9182"
  },
  {
    "period": "2020.9.10",
    "index": "117.0856"
  },
  {
    "period": "2020.9.11",
    "index": "84.6034"
  },
  {
    "period": "2020.9.12",
    "index": "86.0454"
  },
  {
    "period": "2020.9.13",
    "index": "95.7249"
  },
  {
    "period": "2020.9.14",
    "index": "102.6168"
  },
  {
    "period": "2020.9.15",
    "index": "99.2898"
  },
  {
    "period": "2020.9.16",
    "index": "99.325"
  },
  {
    "period": "2020.9.17",
    "index": "96.4034"
  },
  {
    "period": "2020.9.18",
    "index": "79.0966"
  },
  {
    "period": "2020.9.19",
    "index": "74.742"
  },
  {
    "period": "2020.9.20",
    "index": "91.2109"
  },
  {
    "period": "2020.9.21",
    "index": "94.8016"
  },
  {
    "period": "2020.9.22",
    "index": "91.4732"
  },
  {
    "period": "2020.9.23",
    "index": "86.6274"
  },
  {
    "period": "2020.9.24",
    "index": "81.8181"
  },
  {
    "period": "2020.9.25",
    "index": "72.6159"
  },
  {
    "period": "2020.9.26",
    "index": "65.7334"
  },
  {
    "period": "2020.9.27",
    "index": "80.907"
  },
  {
    "period": "2020.9.28",
    "index": "70.4686"
  },
  {
    "period": "2020.9.29",
    "index": "55.2481"
  },
  {
    "period": "2020.9.30",
    "index": "50.8158"
  },
  {
    "period": "2020.10.1",
    "index": "54.5925"
  },
  {
    "period": "2020.10.2",
    "index": "65.3727"
  },
  {
    "period": "2020.10.3",
    "index": "78.7882"
  },
  {
    "period": "2020.10.4",
    "index": "96.5529"
  },
  {
    "period": "2020.10.5",
    "index": "98.0437"
  },
  {
    "period": "2020.10.6",
    "index": "91.9938"
  },
  {
    "period": "2020.10.7",
    "index": "85.6007"
  },
  {
    "period": "2020.10.8",
    "index": "75.1799"
  },
  {
    "period": "2020.10.9",
    "index": "69.7905"
  },
  {
    "period": "2020.10.10",
    "index": "74.1171"
  },
  {
    "period": "2020.10.11",
    "index": "88.1755"
  },
  {
    "period": "2020.10.12",
    "index": "90.7684"
  },
  {
    "period": "2020.10.13",
    "index": "87.6744"
  },
  {
    "period": "2020.10.14",
    "index": "87.515"
  },
  {
    "period": "2020.10.15",
    "index": "79.4898"
  },
  {
    "period": "2020.10.16",
    "index": "72.2927"
  },
  {
    "period": "2020.10.17",
    "index": "65.7023"
  },
  {
    "period": "2020.10.18",
    "index": "81.3034"
  },
  {
    "period": "2020.10.19",
    "index": "89.0735"
  },
  {
    "period": "2020.10.20",
    "index": "86.9123"
  },
  {
    "period": "2020.10.21",
    "index": "85.5971"
  },
  {
    "period": "2020.10.22",
    "index": "78.1448"
  },
  {
    "period": "2020.10.23",
    "index": "68.5606"
  },
  {
    "period": "2020.10.24",
    "index": "61.4095"
  },
  {
    "period": "2020.10.25",
    "index": "74.6882"
  },
  {
    "period": "2020.10.26",
    "index": "85.5158"
  },
  {
    "period": "2020.10.27",
    "index": "83.4873"
  },
  {
    "period": "2020.10.28",
    "index": "80.4411"
  },
  {
    "period": "2020.10.29",
    "index": "78.5823"
  },
  {
    "period": "2020.10.30",
    "index": "67.0771"
  },
  {
    "period": "2020.10.31",
    "index": "59.8456"
  },
  {
    "period": "2020.11.1",
    "index": "83.6986"
  },
  {
    "period": "2020.11.2",
    "index": "86.6035"
  },
  {
    "period": "2020.11.3",
    "index": "83.453"
  },
  {
    "period": "2020.11.4",
    "index": "79.5873"
  },
  {
    "period": "2020.11.5",
    "index": "75.1759"
  },
  {
    "period": "2020.11.6",
    "index": "69.437"
  },
  {
    "period": "2020.11.7",
    "index": "62.5631"
  },
  {
    "period": "2020.11.8",
    "index": "76.7461"
  },
  {
    "period": "2020.11.9",
    "index": "84.9898"
  },
  {
    "period": "2020.11.10",
    "index": "81.0926"
  },
  {
    "period": "2020.11.11",
    "index": "79.4623"
  },
  {
    "period": "2020.11.12",
    "index": "78.7444"
  },
  {
    "period": "2020.11.13",
    "index": "67.9444"
  },
  {
    "period": "2020.11.14",
    "index": "49.15399933"
  },
  {
    "period": "2020.11.15",
    "index": "48.72503662"
  },
  {
    "period": "2020.11.16",
    "index": "52.94184875"
  },
  {
    "period": "2020.11.17",
    "index": "58.16291046"
  },
  {
    "period": "2020.11.18",
    "index": "61.19716644"
  },
  {
    "period": "2020.11.19",
    "index": "60.77416229"
  },
  {
    "period": "2020.11.20",
    "index": "59.95639038"
  },
  {
    "period": "2020.11.21",
    "index": "60.44877625"
  },
  {
    "period": "2020.11.22",
    "index": "61.24419403"
  },
  {
    "period": "2020.11.23",
    "index": "64.02313232"
  },
  {
    "period": "2020.11.24",
    "index": "66.28288269"
  },
  {
    "period": "2020.11.25",
    "index": "66.20058441"
  },
  {
    "period": "2020.11.26",
    "index": "64.86445618"
  },
  {
    "period": "2020.11.27",
    "index": "63.36710358"
  },
  {
    "period": "2020.11.28",
    "index": "63.90874481"
  },
  {
    "period": "2020.11.29",
    "index": "65.39479828"
  },
  {
    "period": "2020.11.30",
    "index": "66.28089142"
  },
  {
    "period": "2020.12.1",
    "index": "65.93354034"
  },
  {
    "period": "2020.12.2",
    "index": "62.90193939"
  },
  {
    "period": "2020.12.3",
    "index": "59.02658844"
  },
  {
    "period": "2020.12.4",
    "index": "55.72241974"
  },
  {
    "period": "2020.12.5",
    "index": "54.55432892"
  },
  {
    "period": "2020.12.6",
    "index": "55.70228577"
  },
  {
    "period": "2020.12.7",
    "index": "57.20222473"
  },
  {
    "period": "2020.12.8",
    "index": "58.44720459"
  },
  {
    "period": "2020.12.9",
    "index": "57.98566437"
  },
  {
    "period": "2020.12.10",
    "index": "58.10007477"
  },
  {
    "period": "2020.12.11",
    "index": "59.09807587"
  },
  {
    "period": "2020.12.12",
    "index": "60.01235962"
  }
]